pyrofiler/__init__.py
pyrofiler/callbacks.py
pyrofiler/contextmanagers.py
pyrofiler/decorators_background.py
pyrofiler/decorators_foreground.py
pyrofiler/measures.py
pyrofiler/pyrofiler.py
pyrofiler/threading.py
pyrofiler/tools.py
pyrofiler/c/__init__.py
pyrofiler/d/__init__.py
pyrofiler-0.1.11.dist-info/LICENSE
pyrofiler-0.1.11.dist-info/METADATA
pyrofiler-0.1.11.dist-info/WHEEL
pyrofiler-0.1.11.dist-info/top_level.txt
pyrofiler-0.1.11.dist-info/RECORD
