Metadata-Version: 2.1
Name: pyrofiler
Version: 0.1.11
Summary: Toolset for granular and live profiling
Home-page: https://github.com/DaniloZZZ/pyrofiler
Author: Dan Lykov
Author-email: lkv97dn@gmail.com
License: MIT license
Keywords: pyrofiler
Classifier: Development Status :: 2 - Pre-Alpha
Classifier: Intended Audience :: Developers
Classifier: License :: OSI Approved :: MIT License
Classifier: Natural Language :: English
Classifier: Programming Language :: Python :: 3
Classifier: Programming Language :: Python :: 3.5
Classifier: Programming Language :: Python :: 3.6
Classifier: Programming Language :: Python :: 3.7
Classifier: Programming Language :: Python :: 3.8
Requires-Python: >=3.5
License-File: LICENSE
Requires-Dist: psutil
